miscale/__init__.py
miscale/body_composition.py
miscale/miscale.py
test/__init__.py
test/test_miscale.py
miscale-0.1.1.dist-info/METADATA
miscale-0.1.1.dist-info/WHEEL
miscale-0.1.1.dist-info/top_level.txt
miscale-0.1.1.dist-info/RECORD
