Metadata-Version: 2.1
Name: miscale
Version: 0.1.1
Summary: A library to receive data from Xiaomi Body Composition Scale.
Home-page: https://github.com/bauerj/miscale
Author: Johann Bauer
Author-email: bauerj@bauerj.eu
License: MIT
Platform: UNKNOWN
Classifier: License :: OSI Approved :: MIT License
Classifier: Programming Language :: Python
Classifier: Programming Language :: Python :: 3
Classifier: Programming Language :: Python :: 3.7
Requires-Python: >=3.5.0
Requires-Dist: bluepy
